uniem/__init__.py
uniem/criteria.py
uniem/data.py
uniem/data_structures.py
uniem/finetuner.py
uniem/integration/__init__.py
uniem/integration/sentence_transformers_wrapper.py
uniem/model.py
uniem/trainer.py
uniem/training_strategy.py
uniem/types.py
uniem/utils.py
uniem/version.py
uniem-0.3.3.dist-info/LICENSE
uniem-0.3.3.dist-info/METADATA
uniem-0.3.3.dist-info/WHEEL
uniem-0.3.3.dist-info/RECORD
