Metadata-Version: 2.1
Name: uniem
Version: 0.3.3
Summary: unified embedding model
License: MIT
Author: wangyuxin
Author-email: wangyuxin@mokahr.com
Requires-Python: >=3.10,<4.0
Classifier: License :: OSI Approved :: MIT License
Classifier: Programming Language :: Python :: 3
Classifier: Programming Language :: Python :: 3.10
Classifier: Programming Language :: Python :: 3.11
Requires-Dist: accelerate (>=0.21.0,<0.22.0)
Requires-Dist: datasets (>=2.12.0,<3.0.0)
Requires-Dist: tqdm (>=4.65.0,<5.0.0)
Requires-Dist: transformers (>=4.28.0,<5.0.0)
Requires-Dist: typer[all] (>=0.9.0,<0.10.0)
